setup.py
bin/cloudctl
cld.egg-info/PKG-INFO
cld.egg-info/SOURCES.txt
cld.egg-info/dependency_links.txt
cld.egg-info/not-zip-safe
cld.egg-info/top_level.txt
cloudctl/__init__.py
cloudctl/arguments.py
cloudctl/aws.py
cloudctl/chart.py
cloudctl/cluster.py
cloudctl/input.py
cloudctl/output.py
cloudctl/process.py