Metadata-Version: 1.0
Name: cld
Version: 0.1.3
Summary: Tool to manage Kubernetes clusters and helm charts across multiple AWS accounts and clusters
Home-page: UNKNOWN
Author: UNKNOWN
Author-email: UNKNOWN
License: UNKNOWN
Platform: UNKNOWN
